{
  "tasks": [
    {
      "title": "React",
      "creator": "Quang",
      "desc": "Học react qua youtube",
      "id": 1
    },
    {
      "title": "HTML",
      "creator": "Quang",
      "desc": "Học HTML qua F8",
      "id": 2
    },
    {
      "title": "HTML",
      "creator": "Quang",
      "desc": "Học HTML qua F8",
      "id": 3
    },
    {
      "title": "Test",
      "creator": "Hai quynh",
      "desc": "Học HTML qua FB",
      "id": 7
    },
    {
      "type": "ADD_TASKS_REQUEST",
      "payload": {
        "title": "Test2",
        "creator": "Hai quynh",
        "desc": "Học HTML qua Sách"
      },
      "id": 8
    },
    {
      "type": "ADD_TASKS_REQUEST",
      "payload": {
        "title": "Test2",
        "creator": "Hai quynh",
        "desc": "Học HTML qua Sách"
      },
      "id": 9
    },
    {
      "type": "ADD_TASKS_REQUEST",
      "payload": {
        "title": "Test2",
        "creator": "Hai quynh",
        "desc": "Học HTML qua Sách"
      },
      "id": 10
    },
    {
      "title": "Pharmacis",
      "creator": "sushi",
      "desc": "test",
      "id": 27
    }
  ]
}